common/__init__.py
common/app_settings.json
common/get_api.py
common/tln_exceptions.py
interface/__init__.py
interface/cli/__init__.py
interface/cli/cli.py
news/__init__.py
news/src/__init__.py
news/src/google_news.py
news_cli-1.0.3.dist-info/METADATA
news_cli-1.0.3.dist-info/WHEEL
news_cli-1.0.3.dist-info/entry_points.txt
news_cli-1.0.3.dist-info/top_level.txt
news_cli-1.0.3.dist-info/RECORD
