Metadata-Version: 2.1
Name: news-cli
Version: 1.0.3
Summary: A cli app to get news snapshots
Home-page: https://gitlab.com/ygivenx/the-news-app
Author: Shubhi Rani & Rohan Singh
Author-email: shubhirohan@yandex.com
License: UNKNOWN
Platform: UNKNOWN
Classifier: Programming Language :: Python :: 3
Classifier: License :: OSI Approved :: MIT License
Classifier: Operating System :: OS Independent
Requires-Python: >=3.0
Requires-Dist: Click
Requires-Dist: prettytable
Requires-Dist: requests
